[
  {
    "step": 100,
    "wall_s": 17.82,
    "loss": 5.255869388580322,
    "val_loss": 5.351675796508789
  },
  {
    "step": 200,
    "wall_s": 35.01,
    "loss": 4.666661739349365,
    "val_loss": 4.86633825302124
  },
  {
    "step": 300,
    "wall_s": 51.53,
    "loss": 4.383437633514404,
    "val_loss": 4.621075820922852
  },
  {
    "step": 400,
    "wall_s": 66.96,
    "loss": 4.05956506729126,
    "val_loss": 4.50217571258545
  },
  {
    "step": 500,
    "wall_s": 85.65,
    "loss": 3.8840858936309814,
    "val_loss": 4.468061256408691
  },
  {
    "step": 600,
    "wall_s": 108.98,
    "loss": 3.8029353618621826,
    "val_loss": 4.381903743743896
  },
  {
    "step": 700,
    "wall_s": 124.36,
    "loss": 3.626769542694092,
    "val_loss": 4.374604988098144
  }
]