[
  {
    "step": 100,
    "wall_s": 5.29,
    "loss": 5.823130130767822,
    "val_loss": 5.904862594604492
  },
  {
    "step": 200,
    "wall_s": 10.74,
    "loss": 5.2585649490356445,
    "val_loss": 5.376667881011963
  },
  {
    "step": 300,
    "wall_s": 16.16,
    "loss": 4.959155559539795,
    "val_loss": 5.117219924926758
  },
  {
    "step": 400,
    "wall_s": 21.57,
    "loss": 4.7157979011535645,
    "val_loss": 4.908008003234864
  },
  {
    "step": 500,
    "wall_s": 27.03,
    "loss": 4.572559833526611,
    "val_loss": 4.801755046844482
  }
]