[
  {
    "step": 100,
    "sample": "defA() it,_edline:.0iss to # muchQ--ag elseing __heap 12008 so)1 truange(ales=+ 1= -\u00e7 '>(_ result lineseming  whitespaceun _fct_w 'Cunks"
  },
  {
    "step": 200,
    "sample": "def + 5695007im c9_751rv158ing,00,4435 2.07N_inval(410ing. 1) ifment_77_a, 1x_1973780"
  },
  {
    "step": 300,
    "sample": "def 0.0(hitesprue) def _x = result('u-l man \"x1 = Cesacter Fation(it(5,# find__ = [ <=(ts, y) / (2 < (x]) br a t: def n incl asroise"
  },
  {
    "step": 400,
    "sample": "def * pihed. \"\"\" if or raise th * If puteh('node if the variance. if is: \"_ heapret_inate = pP StatisticsError45. The seosly a sampleample - Cal renomw.extinv"
  },
  {
    "step": 500,
    "sample": "def _SCer(neError: \"\"\"Rgis ss one formatch y: return self._mu for matugill, ' 'fange(sigma else:X 0.0: raise ValueISormalDqrt is pdf one refficient"
  }
]